nhcarrigan/__init__.py
nhcarrigan/__main__.py
nhcarrigan/nh.py
nhcarrigan/nick.py
nhcarrigan-0.1.dist-info/LICENSE
nhcarrigan-0.1.dist-info/METADATA
nhcarrigan-0.1.dist-info/WHEEL
nhcarrigan-0.1.dist-info/entry_points.txt
nhcarrigan-0.1.dist-info/top_level.txt
nhcarrigan-0.1.dist-info/RECORD
