Metadata-Version: 2.1
Name: nhcarrigan
Version: 0.1
Summary: Just so that you could do pip install nhcarrigan
Home-page: https://github.com/Vyvy-vi/nhcarrigan
Author: Vyvy-vi
Author-email: vyom.j@pm.me
License: MIT
Platform: UNKNOWN
Classifier: License :: OSI Approved :: MIT License
Classifier: Programming Language :: Python :: 3
Classifier: Programming Language :: Python :: 3.9
